{"State.7c7b9fb4-50b2-4739-8811-a57a01cfc008": {"id": "7c7b9fb4-50b2-4739-8811-a57a01cfc008", "created_at": "2024-03-18T18:14:32.420010", "updated_at": "2024-03-18T18:14:32.420237", "__class__": "State"}, "State.2d13e04f-b1a4-4ef5-94ef-850f179ffd29": {"id": "2d13e04f-b1a4-4ef5-94ef-850f179ffd29", "created_at": "2024-03-18T18:14:32.422572", "updated_at": "2024-03-18T18:14:32.422775", "__class__": "State"}, "State.55a9b90c-0ab9-4c38-9c93-85be53b471e8": {"name": "California", "id": "55a9b90c-0ab9-4c38-9c93-85be53b471e8", "created_at": "2024-03-18T18:15:43.975315", "updated_at": "2024-03-18T18:15:43.975562", "__class__": "State"}, "State.ad6ee2bb-53a7-43af-8eff-54aa26b71889": {"name": "Arizona", "id": "ad6ee2bb-53a7-43af-8eff-54aa26b71889", "created_at": "2024-03-18T18:15:43.978595", "updated_at": "2024-03-18T18:15:43.978814", "__class__": "State"}, "Place.6efebd65-b9dc-4127-8f69-8b1a0ed9ad40": {"city_id": "0001", "user_id": "0001", "name": "My little house", "number_rooms": 4, "number_bathrooms": 2, "max_guest": 10, "price_by_night": 300, "latitude": 37.773972, "longitude": -122.431297, "id": "6efebd65-b9dc-4127-8f69-8b1a0ed9ad40", "created_at": "2024-03-18T18:15:43.992625", "updated_at": "2024-03-18T18:15:43.992851", "__class__": "Place"}}